Workbook

Sheet Read Me First
B2: State Constitutional Analysis
B4: De jure comparison of South Carolina, Tennessee, Texas, and Utah — Hybrid Tidy + Presentation (Option C)
B6: Version: Draft 1.0 — May 2026
B9: Purpose | C9: This workbook contains a de jure comparative analysis of the state constitutions of South Carolina, Tennessee, Texas, and Utah, with the goal of supporting selection of a pilot state for a study on Fundamental Freedoms, Checks and Balances, and Democratic Protections.
B10: Scope and limitations | C10: This is a TEXTUAL analysis (de jure). It does NOT capture: (a) judicial interpretation of constitutional clauses, (b) statutory implementation, (c) enforcement practice, or (d) political dynamics. A clause present in the text may be unenforceable (e.g., religious tests for office under Torcaso v. Watkins) or interpreted in ways that diverge from its plain reading.
B11: Dimensions | C11: Three dimensions are assessed: (1) Fundamental Freedoms — individual rights and protections; (2) Checks and Balances — institutional accountability among branches; (3) Democratic Protections — popular sovereignty mechanisms and electoral rights.
B12: Scoring system | C12: Each indicator is scored 0–3 on an ordinal scale where HIGHER = stronger democratic protection, more robust check, or more inclusive freedom. The direction is explicitly defined per indicator in the 'Scoring guidance' field. Use this as a starting point for discussion, not as a final ranking.
B13: Score interpretation | C13: 0 = Absent, regressive, or strongly weakening provision. 1 = Weak or partially compromised provision. 2 = Moderate or standard provision. 3 = Strong or expansive provision.
B14: Methodological caveat | C14: Aggregate scores by dimension are simple sums and treat all indicators as equally weighted. This is a deliberate simplification; weighted scoring would require explicit value choices about which protections matter most. Reviewers are encouraged to recompute aggregates using their preferred weights.
B15: Sources | C15: Primary: 50constitutions.org (State Democracy Research Initiative, UW Law School), Ballotpedia, state Justia compilations, state legislative websites. Secondary: Brennan Center, State Court Report, The Sentencing Project, and other comparative analyses cited in the Sources sheet.
B16: Citation | C16: If used in published work, cite as: [Your Project Name]. (2026). State Constitutional Analysis: De Jure Comparative of SC/TN/TX/UT. Internal working document.

Sheet Executive Summary
B2: Executive Summary — Aggregate Scores by Dimension
B4: Each cell shows the SUM of indicator scores within that dimension for that state. Maximum possible scores: FF=21, CB=24, DP=21, Total=66. Higher = stronger democratic profile on this dimension (per the scoring direction defined per indicator).
B6: Dimension | C6: SC | D6: TN | E6: TX | F6: UT | G6: Max possible
B7: Fundamental Freedoms | C7: ='FF — Comparative'!C26 -> 13 | D7: ='FF — Comparative'!D26 -> 10 | E7: ='FF — Comparative'!E26 -> 11 | F7: ='FF — Comparative'!F26 -> 16 | G7: 21
B8: Checks and Balances | C8: ='CB — Comparative'!C29 -> 13 | D8: ='CB — Comparative'!D29 -> 11 | E8: ='CB — Comparative'!E29 -> 16 | F8: ='CB — Comparative'!F29 -> 20 | G8: 24
B9: Democratic Protections | C9: ='DP — Comparative'!C26 -> 4 | D9: ='DP — Comparative'!D26 -> 7 | E9: ='DP — Comparative'!E26 -> 5 | F9: ='DP — Comparative'!F26 -> 10 | G9: 21
B10: TOTAL (de jure profile) | C10: =SUM(C7:C9) -> 30 | D10: =SUM(D7:D9) -> 28 | E10: =SUM(E7:E9) -> 32 | F10: =SUM(F7:F9) -> 46 | G10: 66
B13: How to read this dashboard
B14: Aggregate scores are SUMS of indicator scores, with all indicators equally weighted. This produces a comparable 'de jure profile' but should not be over-interpreted: (1) some indicators are more consequential than others, (2) constitutional text does not capture practice, and (3) a low score is not necessarily 'bad' for pilot selection — high contrast between states is often more valuable than a single winner. See the per-dimension sheets for indicator-level detail and the per-state profiles (if present) for narrative context.

Sheet FF — Comparative
A1: Fundamental Freedoms — De jure comparative
A3: ID | B3: Indicator | C3: SC | D3: TN | E3: TX | F3: UT | G3: Question | H3: Scoring guidance
A4: FF01 | B4: Rights placement and structural prominence | C4: 2 | D4: 3 | E4: 3 | F4: 3 | G4: Where in the constitution is the Declaration of Rights located, and how prominently? | H4: 0=Absent or buried; 1=Present but late; 2=Article I, basic; 3=Article I, comprehensive, before government structure
B5: Constitutional reference: | C5: Article I (24 sec.) | D5: Article I (36 sec.) | E5: Article 1 (34 sec.) | F5: Article I
B6: Notes: | C6: Declaration of Rights at Article I, comprehensively reformed in 1971. | D6: Rights enumerated in Article I BEFORE Article II on distribution of powers; explicitly individualist tradition. | E6: Every provision of federal Bill of Rights has a counterpart; placed at front of constitution. | F6: Original 1895 Declaration of Rights largely intact while rest of constitution heavily revised.
A7: FF02 | B7: Equal protection / non-discrimination clause | C7: 2 | D7: 2 | E7: 2 | F7: 2 | G7: Does the constitution have an explicit equal protection or non-discrimination clause? | H7: 0=None; 1=General reference; 2=Explicit clause similar to 14th Amendment; 3=Explicit + enumerated protected categories (gender, race, etc.)
B8: Constitutional reference: | C8: Article I §3 | D8: Article I §8 + Article XI §8 | E8: Article 1 §3, §3a | F8: Article I §24
B9: Notes: | C9: Explicit due process and equal protection clause; no enumerated categories. | D9: Equal protection via class legislation prohibition; interpreted as duplicative of federal 14th Amendment. | E9: Equal rights clause + Equal Rights Amendment (1972) prohibiting discrimination by sex, race, color, creed, national origin. | F9: Uniform operation of laws clause; courts have interpreted it as functional equal protection.
A10: FF03 | B10: Privacy right (explicit or interpretively recognized) | C10: 1 | D10: 1 | E10: 1 | F10: 1 | G10: Does the constitution recognize a right to privacy, explicitly or via interpretation? | H10: 0=No recognition; 1=Implicit via due process only; 2=Implicit, broadly interpreted by courts; 3=Explicit textual right to privacy
B11: Constitutional reference: | C11: Article I §10 | D11: Article I §7, §8 | E11: Article 1 §9 | F11: Article I §14
B12: Notes: | C12: No explicit privacy clause; protections derived from search and seizure provisions only. | D12: TN Supreme Court historically read broad privacy into Section 8; narrowed by 2014 §36 amendment carving out abortion. | E12: No explicit privacy right; derived from search and seizure and due course of law provisions. | F12: No explicit privacy right; derived from search and seizure protections.
A13: FF04 | B13: Religious freedom and church-state separation | C13: 2 | D13: 1 | E13: 1 | F13: 3 | G13: How strong is the religious freedom guarantee and church-state separation? | H13: 0=State religion specified; 1=Freedom + qualifiers; 2=Freedom + secular framing; 3=Freedom + explicit separation, no exclusionary clauses
B14: Constitutional reference: | C14: Article I §2 | D14: Article I §3 + Article IX §1, §2 | E14: Article 1 §4, §6, §7 | F14: Article I §4
B15: Notes: | C15: Religious freedom guaranteed; no state religion; some historical exclusionary clauses cleaned up. | D15: Strong freedom clause BUT Article IX disqualifies clergy from legislature and atheists from any state office (textually present though unenforceable per Torcaso v. Watkins). | E15: Religious freedom guaranteed BUT §4 contains "provided he acknowledge the existence of a Supreme Being" qualifier (unenforceable but textually present). | F15: Strong religious freedom clause; explicit church-state separation; no exclusionary clauses despite religious founding context.
A16: FF05 | B16: Religious test for public office (textual exclusion) | C16: 2 | D16: 0 | E16: 1 | F16: 3 | G16: Does the constitutional text contain any religious test or exclusion for public office? | H16: 0=Active exclusion of non-believers in text; 1=Qualifier (e.g., must believe in Supreme Being); 2=Test prohibited but with caveats; 3=Clean prohibition, no exclusions
B17: Constitutional reference: | C17: Article VI | D17: Article IX §2 | E17: Article 1 §4 | F17: Article I §4
B18: Notes: | C18: Religious test prohibited; some historical qualifiers reformed. | D18: "No person who denies the being of God, or a future state of rewards and punishments, shall hold any office in the civil department of this State." Unenforceable but text remains. | E18: "No religious test shall ever be required... provided he acknowledge the existence of a Supreme Being." Unenforceable but text remains. | F18: Clean prohibition on religious tests; no exclusionary text.
A19: FF06 | B19: Right to bail and pre-trial release | C19: 2 | D19: 3 | E19: 1 | F19: 2 | G19: How robust is the right to bail / pre-trial release in the constitutional text? | H19: 0=No right or extensive exceptions; 1=Right with progressive textual erosion; 2=Right with standard exceptions (capital cases); 3=Strong right, narrow exceptions only
B20: Constitutional reference: | C20: Article I §15 | D20: Article I §15 | E20: Article 1 §11 | F20: Article I §8
B21: Notes: | C21: Bail right with denial for capital offenses and certain violent offenses. | D21: "All prisoners shall be bailable by sufficient sureties, unless for capital offences when the proof is evident, or the presumption great." TN SC has interpreted bail as mandatory except in capital cases. | E21: Bail right amended five times between 1956 and 2024, each time expanding circumstances for denial. Pattern of textual erosion. | F21: Bail right with standard exceptions for capital cases and certain violent offenses.
A22: FF07 | B22: Constitutional treatment of abortion / reproductive rights | C22: 2 | D22: 0 | E22: 2 | F22: 2 | G22: Does the constitution explicitly address (protect, exclude, or remain silent on) reproductive rights? | H22: 0=Explicitly excluded as a right; 1=Silent and narrowly interpreted; 2=Silent but not foreclosed; 3=Explicitly protected
B23: Constitutional reference: | C23: No specific provision | D23: Article I §36 (2014) | E23: No specific provision | F23: No specific provision
B24: Notes: | C24: Constitution silent; subject to legislation and litigation. | D24: "Nothing in this Constitution secures or protects a right to abortion or requires the funding of an abortion." Explicit textual subtraction. | E24: Constitution silent; statutory ban in place, no constitutional carve-out yet. | F24: Constitution silent; statutory framework in litigation.
B26: Aggregate FF score (sum) | C26: =SUM(C4,C7,C10,C13,C16,C19,C22) -> 13 | D26: =SUM(D4,D7,D10,D13,D16,D19,D22) -> 10 | E26: =SUM(E4,E7,E10,E13,E16,E19,E22) -> 11 | F26: =SUM(F4,F7,F10,F13,F16,F19,F22) -> 16 | G26: Max possible: 21

Sheet CB — Comparative
A1: Checks and Balances — De jure comparative
A3: ID | B3: Indicator | C3: SC | D3: TN | E3: TX | F3: UT | G3: Question | H3: Scoring guidance
A4: CB01 | B4: Plural executive (independently elected statewide officials) | C4: 3 | D4: 1 | E4: 3 | F4: 2 | G4: How many statewide executive officials are independently elected (not appointed by Governor)? | H4: 0=Single executive (only Gov); 1=2-3 officials; 2=4-5 officials; 3=6+ officials (fragmented executive)
B5: Constitutional reference: | C5: Article VI | D5: Article III, VII | E5: Article 4 | F5: Article VII §1
B6: Notes: | C6: 9 independently elected: Governor, Lt Gov (joint ticket since 2018), Sec State, AG, Treasurer, Comptroller General, Adjutant General, Superintendent of Education, Commissioner of Agriculture. | D6: Only Governor popularly elected statewide; Sec State, Treasurer, Comptroller elected by General Assembly. Lt Gov role filled by Senate Speaker. | E6: 6+ independently elected: Governor, Lt Gov, AG, Comptroller, Land Commissioner, Agriculture Commissioner, Railroad Commission (3); only Sec State appointed by Governor. | F6: 5 elected officials: Governor + Lt Gov (joint ticket), AG, State Auditor, State Treasurer.
A7: CB02 | B7: Attorney General independence from Governor | C7: 3 | D7: 2 | E7: 3 | F7: 3 | G7: How is the state Attorney General selected, and how independent from the Governor? | H7: 0=Appointed by Governor; 1=Appointed by legislature; 2=Appointed by judiciary (unique case); 3=Independently elected by voters
B8: Constitutional reference: | C8: Article VI §7 | D8: Article VI §5 | E8: Article 4 §22 | F8: Article VII §1, §16
B9: Notes: | C9: AG independently elected statewide. | D9: AG appointed by Tennessee Supreme Court for 8-year term. UNIQUE in the US: AG is an officer of the judicial branch, not the executive. Independent from Governor but captured by Supreme Court. | E9: AG independently elected statewide. | F9: AG independently elected statewide.
A10: CB03 | B10: Judicial selection method (high court) | C10: 0 | D10: 3 | E10: 1 | F10: 3 | G10: How are state supreme court justices selected? | H10: 0=Legislative appointment (captured by legislature); 1=Partisan elections (politicized); 2=Gubernatorial appointment alone; 3=Merit selection commission + retention (insulated)
B11: Constitutional reference: | C11: Article V §3 | D11: Article VI §3 + 2014 Amendment 2 | E11: Article 5 §2 | F11: Article VIII §8
B12: Notes: | C12: Justices elected by General Assembly (legislature). Only SC and VA use this method. Until 2000, all justices were former General Assembly members. | D12: Tennessee Plan: nominating commission + gubernatorial appointment + legislative confirmation + retention elections. | E12: Partisan elections for supreme court justices. Highly politicized. | F12: Judicial nominating commission + gubernatorial appointment + Senate confirmation + retention elections.
A13: CB04 | B13: Judicial independence from legislative branch | C13: 0 | D13: 2 | E13: 3 | F13: 2 | G13: Does the legislative branch dominate judicial selection or judicial discipline? | H13: 0=Legislature controls selection and discipline; 1=Legislature confirms appointees; 2=Limited legislative role; 3=No legislative role in selection or discipline
B14: Constitutional reference: | C14: Article V §3, §13 | D14: Article VI | E14: Article 5 | F14: Article VIII §8
B15: Notes: | C15: JMSC is dominated by legislators; legislators have appointed family members. Most justices historically were former legislators. | D15: Legislature confirms gubernatorial appointees (post-2014); does not select directly. | E15: No legislative role in initial selection; voters decide directly. | F15: Senate confirmation required but selection through commission process.
A16: CB05 | B16: Lieutenant Governor power and accountability | C16: 2 | D16: 0 | E16: 0 | F16: 3 | G16: How is the Lt Governor selected and how much power does the office concentrate? | H16: 0=Lt Gov is Senate Speaker (fusion of powers) OR independently elected with major leg/exec powers; 1=Independently elected, modest role; 2=Joint ticket, ceremonial role; 3=Joint ticket, modest succession-only role
B17: Constitutional reference: | C17: Article IV §8 | D17: Article II + Article III | E17: Article 4 §16-17 | F17: Article VII §1, §2
B18: Notes: | C18: Lt Gov elected on joint ticket with Governor since 2018; ceremonial role. | D18: No separate Lt Gov office; Speaker of Senate serves in that role. Fusion of executive succession with legislative leadership. | E18: Lt Gov independently elected; presides over Senate as day-to-day leader (not ceremonial), chairs Legislative Budget Board, sits on Legislative Redistricting Board. Concentrates extraordinary cross-branch power. | F18: Lt Gov elected on joint ticket with Governor; modest role primarily focused on elections administration.
A19: CB06 | B19: Veto override threshold | C19: 2 | D19: 0 | E19: 2 | F19: 2 | G19: What legislative threshold is required to override a gubernatorial veto? | H19: 0=Simple majority (weak veto); 1=3/5 majority; 2=2/3 majority (standard); 3=3/4 or higher
B20: Constitutional reference: | C20: Article IV §21 | D20: Article III §18 | E20: Article 4 §14 | F20: Article VII §8
B21: Notes: | C21: 2/3 of each chamber required to override. | D21: Simple majority of all members elected to each house — SAME threshold as initial passage. Weakest gubernatorial veto in the four states. | E21: 2/3 of each chamber required to override. | F21: 2/3 of each chamber required to override.
A22: CB07 | B22: Constitutional judicial conduct/discipline body | C22: 1 | D22: 1 | E22: 2 | F22: 3 | G22: Is there a constitutionally established body to discipline judges? | H22: 0=No body or only legislative impeachment; 1=Statutory body only; 2=Constitutional body, limited powers; 3=Constitutional body, comprehensive powers
B23: Constitutional reference: | C23: Article V §13 | D23: Statutory (Tenn. Code §17-5-101) | E23: Article 5 §1-a | F23: Article VIII §13
B24: Notes: | C24: Commission on Judicial Conduct exists but legislative dominance over judiciary creates structural tension. | D24: Board of Judicial Conduct exists by statute, not constitution. | E24: State Commission on Judicial Conduct established constitutionally; investigates and recommends discipline. | F24: Judicial Conduct Commission constitutionally established (1984); comprehensive powers including recommendation of removal to Supreme Court.
A25: CB08 | B25: Single-subject rule for legislation | C25: 2 | D25: 2 | E25: 2 | F25: 2 | G25: Does the constitution require each law/amendment to address only a single subject? | H25: 0=No rule; 1=Weak or narrowly applied; 2=Applies to legislation; 3=Applies to legislation AND constitutional amendments
B26: Constitutional reference: | C26: Article III §17 | D26: Article II §17 | E26: Article 3 §35 | F26: Article VI §22
B27: Notes: | C27: "Every Act or resolution having the force of law shall relate to but one subject." | D27: Single-subject rule for legislation; enforcement variable. | E27: Single-subject rule; applies to bills. | F27: Single-subject rule for legislation.
B29: Aggregate CB score (sum) | C29: =SUM(C4,C7,C10,C13,C16,C19,C22,C25) -> 13 | D29: =SUM(D4,D7,D10,D13,D16,D19,D22,D25) -> 11 | E29: =SUM(E4,E7,E10,E13,E16,E19,E22,E25) -> 16 | F29: =SUM(F4,F7,F10,F13,F16,F19,F22,F25) -> 20 | G29: Max possible: 24

Sheet DP — Comparative
A1: Democratic Protections — De jure comparative
A3: ID | B3: Indicator | C3: SC | D3: TN | E3: TX | F3: UT | G3: Question | H3: Scoring guidance
A4: DP01 | B4: Citizen initiative for statutes | C4: 0 | D4: 0 | E4: 0 | F4: 2 | G4: Can citizens propose statutes through signature petition (statutory initiative)? | H4: 0=No; 1=Yes, but high signature threshold or restrictions; 2=Yes, moderate threshold; 3=Yes, accessible threshold
B5: Constitutional reference: | C5: Not provided | D5: Not provided | E5: Not provided | F5: Article VI §1
B6: Notes: | C6: No statewide initiative process. | D6: No statewide initiative process. | E6: No statewide initiative process. Voters rejected initiative in 1914; no successful adoption since. | F6: Direct citizen initiative for statutes since 1900. Legislature retains amendment power, but constrained by 2024 SC ruling on "alter or reform" right.
A7: DP02 | B7: Citizen initiative for constitutional amendments | C7: 0 | D7: 0 | E7: 0 | F7: 0 | G7: Can citizens propose constitutional amendments directly? | H7: 0=No; 1=Yes, with high threshold; 2=Yes, moderate; 3=Yes, accessible
B8: Constitutional reference: | C8: Article XVI | D8: Article XI §3 | E8: Article 17 | F8: Article XXIII
B9: Notes: | C9: No citizen-initiated constitutional amendments. | D9: No citizen-initiated constitutional amendments. | E9: No citizen-initiated amendments. Only legislative referral. | F9: Citizen initiative applies to statutes only, NOT constitutional amendments.
A10: DP03 | B10: Veto referendum (citizen check on legislation) | C10: 0 | D10: 0 | E10: 0 | F10: 2 | G10: Can citizens petition to suspend/repeal legislative acts via referendum? | H10: 0=No; 1=Yes, with high threshold; 2=Yes, moderate; 3=Yes, accessible
B11: Constitutional reference: | C11: Not provided | D11: Not provided | E11: Not provided | F11: Article VI §1(2)
B12: Notes: | C12: No veto referendum process. | D12: No veto referendum process. | E12: No veto referendum process. | F12: Veto referendum available. Signature gathering period extended to 60 days in 2024.
A13: DP04 | B13: Recall of statewide elected officials | C13: 0 | D13: 1 | E13: 1 | F13: 0 | G13: Can voters recall statewide elected officials via petition? | H13: 0=No; 1=Local only; 2=Limited statewide; 3=Full statewide recall
B14: Constitutional reference: | C14: Not provided | D14: Statutory, local only | E14: Local charters | F14: Not provided
B15: Notes: | C15: No statewide recall mechanism. | D15: Recall available for local officials only; not for state officials. | E15: No statewide recall; some home-rule cities have recall. | F15: No statewide recall mechanism.
A16: DP05 | B16: Constitutional amendment legislative threshold | C16: 2 | D16: 3 | E16: 2 | F16: 2 | G16: How strict is the legislative threshold to refer constitutional amendments? | H16: Note: higher rigidity entrenches existing text (rights or restrictions). 0=Simple majority; 1=3/5; 2=2/3 single session; 3=2/3 across two sessions or higher bar
B17: Constitutional reference: | C17: Article XVI §1 | D17: Article XI §3 | E17: Article 17 §1 | F17: Article XXIII §1
B18: Notes: | C18: 2/3 of each chamber required, single session. | D18: Two consecutive legislative sessions: simple majority first, 2/3 second. Most rigid of the four. | E18: 2/3 of each chamber required, single session. | F18: 2/3 of each chamber required, single session.
A19: DP06 | B19: Constitutional amendment popular ratification threshold | C19: 1 | D19: 3 | E19: 1 | F19: 1 | G19: What popular threshold is required to ratify a constitutional amendment? | H19: 0=No popular vote required; 1=Simple majority of votes on amendment; 2=Majority of votes cast in election; 3=Majority of votes for top-of-ticket (very strict denominator)
B20: Constitutional reference: | C20: Article XVI §1 | D20: Article XI §3 | E20: Article 17 §1 | F20: Article XXIII §1
B21: Notes: | C21: Simple majority of votes on the amendment. | D21: Majority of all citizens voting for governor — strictest denominator among the four. Includes those who voted for governor but not on amendment. | E21: Simple majority of votes on the amendment. | F21: Simple majority of votes on the amendment.
A22: DP07 | B22: Felony disenfranchisement strictness | C22: 1 | D22: 0 | E22: 1 | F22: 3 | G22: How restrictively does the state disenfranchise people with felony convictions? | H22: 0=Lifetime ban for any felony; 1=Until completion of sentence including parole/probation (and beyond); 2=Until completion of incarceration + parole/probation; 3=Only during incarceration
B23: Constitutional reference: | C23: Article II §7 | D23: Article I §5; statutory | E23: Article 6 §1; statutory | F23: Article IV §6
B24: Notes: | C24: Disenfranchisement until completion of incarceration, parole, AND probation. | D24: Among strictest in US. Disenfranchises permanently for certain pre-1973 offenses; complex restoration process for post-1981 felonies. Disenfranchisement rates among highest nationally. | E24: Disenfranchisement until completion of incarceration, parole, AND probation; rights restored automatically thereafter. | F24: Disenfranchisement only during incarceration; restoration automatic upon release. Among least restrictive in US.
B26: Aggregate DP score (sum) | C26: =SUM(C4,C7,C10,C13,C16,C19,C22) -> 4 | D26: =SUM(D4,D7,D10,D13,D16,D19,D22) -> 7 | E26: =SUM(E4,E7,E10,E13,E16,E19,E22) -> 5 | F26: =SUM(F4,F7,F10,F13,F16,F19,F22) -> 10 | G26: Max possible: 21

Sheet Tidy Data
A1: Tidy Data — Long format (one row per indicator × state)
A2: This sheet is structured for analytical use (pivot tables, R/Python imports, regression of scores, etc.). Each row is a unique (indicator, state) observation.
A4: indicator_id | B4: dimension | C4: indicator | D4: state_code | E4: state_name | F4: score | G4: constitutional_ref | H4: note | I4: scoring_guidance
A5: FF01 | B5: Fundamental Freedoms | C5: Rights placement and structural prominence | D5: SC | E5: South Carolina | F5: 2 | G5: Article I (24 sec.) | H5: Declaration of Rights at Article I, comprehensively reformed in 1971. | I5: 0=Absent or buried; 1=Present but late; 2=Article I, basic; 3=Article I, comprehensive, before government structure
A6: FF01 | B6: Fundamental Freedoms | C6: Rights placement and structural prominence | D6: TN | E6: Tennessee | F6: 3 | G6: Article I (36 sec.) | H6: Rights enumerated in Article I BEFORE Article II on distribution of powers; explicitly individualist tradition. | I6: 0=Absent or buried; 1=Present but late; 2=Article I, basic; 3=Article I, comprehensive, before government structure
A7: FF01 | B7: Fundamental Freedoms | C7: Rights placement and structural prominence | D7: TX | E7: Texas | F7: 3 | G7: Article 1 (34 sec.) | H7: Every provision of federal Bill of Rights has a counterpart; placed at front of constitution. | I7: 0=Absent or buried; 1=Present but late; 2=Article I, basic; 3=Article I, comprehensive, before government structure
A8: FF01 | B8: Fundamental Freedoms | C8: Rights placement and structural prominence | D8: UT | E8: Utah | F8: 3 | G8: Article I | H8: Original 1895 Declaration of Rights largely intact while rest of constitution heavily revised. | I8: 0=Absent or buried; 1=Present but late; 2=Article I, basic; 3=Article I, comprehensive, before government structure
A9: FF02 | B9: Fundamental Freedoms | C9: Equal protection / non-discrimination clause | D9: SC | E9: South Carolina | F9: 2 | G9: Article I §3 | H9: Explicit due process and equal protection clause; no enumerated categories. | I9: 0=None; 1=General reference; 2=Explicit clause similar to 14th Amendment; 3=Explicit + enumerated protected categories (gender, race, etc.)
A10: FF02 | B10: Fundamental Freedoms | C10: Equal protection / non-discrimination clause | D10: TN | E10: Tennessee | F10: 2 | G10: Article I §8 + Article XI §8 | H10: Equal protection via class legislation prohibition; interpreted as duplicative of federal 14th Amendment. | I10: 0=None; 1=General reference; 2=Explicit clause similar to 14th Amendment; 3=Explicit + enumerated protected categories (gender, race, etc.)
A11: FF02 | B11: Fundamental Freedoms | C11: Equal protection / non-discrimination clause | D11: TX | E11: Texas | F11: 2 | G11: Article 1 §3, §3a | H11: Equal rights clause + Equal Rights Amendment (1972) prohibiting discrimination by sex, race, color, creed, national origin. | I11: 0=None; 1=General reference; 2=Explicit clause similar to 14th Amendment; 3=Explicit + enumerated protected categories (gender, race, etc.)
A12: FF02 | B12: Fundamental Freedoms | C12: Equal protection / non-discrimination clause | D12: UT | E12: Utah | F12: 2 | G12: Article I §24 | H12: Uniform operation of laws clause; courts have interpreted it as functional equal protection. | I12: 0=None; 1=General reference; 2=Explicit clause similar to 14th Amendment; 3=Explicit + enumerated protected categories (gender, race, etc.)
A13: FF03 | B13: Fundamental Freedoms | C13: Privacy right (explicit or interpretively recognized) | D13: SC | E13: South Carolina | F13: 1 | G13: Article I §10 | H13: No explicit privacy clause; protections derived from search and seizure provisions only. | I13: 0=No recognition; 1=Implicit via due process only; 2=Implicit, broadly interpreted by courts; 3=Explicit textual right to privacy
A14: FF03 | B14: Fundamental Freedoms | C14: Privacy right (explicit or interpretively recognized) | D14: TN | E14: Tennessee | F14: 1 | G14: Article I §7, §8 | H14: TN Supreme Court historically read broad privacy into Section 8; narrowed by 2014 §36 amendment carving out abortion. | I14: 0=No recognition; 1=Implicit via due process only; 2=Implicit, broadly interpreted by courts; 3=Explicit textual right to privacy
A15: FF03 | B15: Fundamental Freedoms | C15: Privacy right (explicit or interpretively recognized) | D15: TX | E15: Texas | F15: 1 | G15: Article 1 §9 | H15: No explicit privacy right; derived from search and seizure and due course of law provisions. | I15: 0=No recognition; 1=Implicit via due process only; 2=Implicit, broadly interpreted by courts; 3=Explicit textual right to privacy
A16: FF03 | B16: Fundamental Freedoms | C16: Privacy right (explicit or interpretively recognized) | D16: UT | E16: Utah | F16: 1 | G16: Article I §14 | H16: No explicit privacy right; derived from search and seizure protections. | I16: 0=No recognition; 1=Implicit via due process only; 2=Implicit, broadly interpreted by courts; 3=Explicit textual right to privacy
... A92: DP07 | B92: Democratic Protections | C92: Felony disenfranchisement strictness | D92: UT | E92: Utah | F92: 3 | G92: Article IV §6 | H92: Disenfranchisement only during incarceration; restoration automatic upon release. Among least restrictive in US. | I92: 0=Lifetime ban for any felony; 1=Until completion of sentence including parole/probation (and beyond); 2=Until completion of incarceration + parole/probation; 3=Only during incarceration

Sheet Sources
B2: Sources and References
B4: # | C4: Source | D4: Publisher / Author | E4: URL
B5: 1 | C5: 50 Constitutions | D5: State Democracy Research Initiative, University of Wisconsin Law School | E5: https://50constitutions.org/
B6: 2 | C6: South Carolina Constitution | D6: South Carolina Legislature | E6: https://www.scstatehouse.gov/scconstitution/scconst.php
B7: 3 | C7: Tennessee Constitution | D7: Tennessee Secretary of State | E7: https://publications.tnsosfiles.com/pub/2023%20TN%20Constitution.pdf
B8: 4 | C8: Texas Constitution | D8: Texas Legislature Online | E8: https://statutes.capitol.texas.gov/?link=CN
B9: 5 | C9: Utah Constitution | D9: Utah State Legislature | E9: https://le.utah.gov/xcode/constitution.html
B10: 6 | C10: Ballotpedia state constitution pages | D10: Ballotpedia | E10: https://ballotpedia.org/
B11: 7 | C11: Legislative Appointments for Judges | D11: Brennan Center for Justice (2017) | E11: https://www.brennancenter.org/our-work/research-reports/legislative-appointments-judges-lessons-south-carolina-virginia-and-rhode
B12: 8 | C12: Tennessee Supreme Court appoints AG | D12: Tennessee Administrative Office of the Courts | E12: https://www.tncourts.gov/
B13: 9 | C13: Expanding the Vote: State Felony Disenfranchisement Reform | D13: The Sentencing Project (2023) | E13: https://www.sentencingproject.org/reports/expanding-the-vote-state-felony-disenfranchisement-reform-1997-2023/
B14: 10 | C14: The Utah Constitution Is 'Distinctively Undistinctive' | D14: State Court Report (2025) | E14: https://statecourtreport.org/our-work/analysis-opinion/utah-constitution-distinctively-undistinctive
B15: 11 | C15: The Tennessee Constitution | D15: State Court Report (2026) | E15: https://statecourtreport.org/our-work/analysis-opinion/tennessee-constitution-least-imperfect-and-most-republican-state
B16: 12 | C16: Comparative Constitutions Project (CCP) Codebook v4.0 | D16: Elkins, Z. & Ginsburg, T. (2022) | E16: https://comparativeconstitutionsproject.org/
